{
	"format_version": "1.8.0",
	"animations": {
		"attack.swing": {
			"animation_length": 0.375,
			"bones": {
				"upper_body": {
					"rotation": {
						"0.0": {
							"vector": [0, 0, 0]
						},
						"0.0833": {
							"vector": [0, 20, 0]
						},
						"0.1667": {
							"vector": [0, 0, 0]
						}
					}
				},
				"right_arm": {
					"rotation": {
						"0.0": {
							"vector": [0, 0, 0]
						},
						"0.0833": {
							"vector": [15, 0, 0]
						},
						"0.1667": {
							"vector": [-110.26256, -9.05754, 4.25058]
						},
						"0.375": {
							"vector": [0, 0, 0]
						}
					}
				},
				"right_forearm": {
					"rotation": {
						"0.0": {
							"vector": [0, 0, 0]
						},
						"0.0833": {
							"vector": [-75, 0, 0]
						},
						"0.1667": {
							"vector": [20, 0, -5]
						},
						"0.375": {
							"vector": [0, 0, 0]
						}
					}
				},
				"left_arm": {
					"rotation": {
						"0.0": {
							"vector": [0, 0, 0]
						},
						"0.0833": {
							"vector": [25, 0, 0]
						},
						"0.375": {
							"vector": [0, 0, 0]
						}
					}
				},
				"left_forearm": {
					"rotation": {
						"0.0": {
							"vector": [0, 0, 0]
						},
						"0.0833": {
							"vector": [-45, 0, 0]
						},
						"0.1667": {
							"vector": [0, 0, 0]
						}
					}
				}
			}
		},
		"move.walk": {
			"loop": true,
			"animation_length": 1,
			"bones": {
				"upper_body": {
					"rotation": {
						"0.0": {
							"vector": [0, 0, 0]
						},
						"0.25": {
							"vector": [15, 0, 0]
						},
						"0.5": {
							"vector": [0, 0, 0]
						},
						"0.75": {
							"vector": [15, 0, 0]
						},
						"1.0": {
							"vector": [0, 0, 0]
						}
					}
				},
				"head": {
					"rotation": {
						"0.0": {
							"vector": [0, 0, 0]
						},
						"0.25": {
							"vector": [-12.5, 0, 0]
						},
						"0.5": {
							"vector": [0, 0, 0]
						},
						"0.75": {
							"vector": [-12.5, 0, 0]
						},
						"1.0": {
							"vector": [0, 0, 0]
						}
					}
				},
				"right_arm": {
					"rotation": {
						"0.0": {
							"vector": [0, 0, 0]
						},
						"0.25": {
							"vector": [5, 0, 0],
							"easing": "linear"
						},
						"0.5": {
							"vector": [0, 0, 0],
							"easing": "linear"
						},
						"0.75": {
							"vector": [-20, 0, 0],
							"easing": "linear"
						},
						"1.0": {
							"vector": [0, 0, 0],
							"easing": "linear"
						}
					}
				},
				"right_forearm": {
					"rotation": {
						"0.0": {
							"vector": [0, 0, 0]
						},
						"0.25": {
							"vector": [10, 0, 0]
						},
						"0.5": {
							"vector": [0, 0, 0]
						},
						"0.75": {
							"vector": [-10, 0, 0]
						},
						"1.0": {
							"vector": [0, 0, 0]
						}
					}
				},
				"left_arm": {
					"rotation": {
						"0.0": {
							"vector": [0, 0, 0]
						},
						"0.25": {
							"vector": [-20, 0, 0],
							"easing": "linear"
						},
						"0.5": {
							"vector": [0, 0, 0],
							"easing": "linear"
						},
						"0.75": {
							"vector": [5, 0, 0],
							"easing": "linear"
						},
						"1.0": {
							"vector": [0, 0, 0],
							"easing": "linear"
						}
					}
				},
				"left_forearm": {
					"rotation": {
						"0.0": {
							"vector": [0, 0, 0]
						},
						"0.25": {
							"vector": [-20, 0, 0],
							"easing": "linear"
						},
						"0.5": {
							"vector": [0, 0, 0],
							"easing": "linear"
						},
						"0.75": {
							"vector": [5, 0, 0],
							"easing": "linear"
						},
						"1.0": {
							"vector": [0, 0, 0],
							"easing": "linear"
						}
					}
				},
				"spine": {
					"rotation": {
						"0.0": {
							"vector": [0, 0, 0]
						},
						"0.25": {
							"vector": [0, 0, -2.5]
						},
						"0.5": {
							"vector": [0, 0, 0]
						},
						"0.75": {
							"vector": [0, 0, 2.5]
						},
						"1.0": {
							"vector": [0, 0, 0]
						}
					}
				},
				"right_leg": {
					"rotation": {
						"0.0": {
							"vector": [0, 0, 0]
						},
						"0.125": {
							"vector": [-45, 0, 0]
						},
						"0.25": {
							"vector": [-40, 0, 0],
							"easing": "linear"
						},
						"0.5": {
							"vector": [0, 0, 0]
						},
						"0.75": {
							"vector": [30, 0, 0],
							"easing": "linear"
						},
						"1.0": {
							"vector": [0, 0, 0],
							"easing": "linear"
						}
					}
				},
				"right_foot": {
					"rotation": {
						"0.0": {
							"vector": [0, 0, 0]
						},
						"0.25": {
							"vector": [40, 0, 0],
							"easing": "linear"
						},
						"0.5": {
							"vector": [0, 0, 0]
						},
						"0.75": {
							"vector": [47.5, 0, 0],
							"easing": "linear"
						},
						"1.0": {
							"vector": [0, 0, 0],
							"easing": "linear"
						}
					}
				},
				"left_leg": {
					"rotation": {
						"0.0": {
							"vector": [0, 0, 0]
						},
						"0.25": {
							"vector": [30, 0, 0],
							"easing": "linear"
						},
						"0.5": {
							"vector": [0, 0, 0]
						},
						"0.625": {
							"vector": [-45, 0, 0]
						},
						"0.75": {
							"vector": [-40, 0, 0],
							"easing": "linear"
						},
						"1.0": {
							"vector": [0, 0, 0],
							"easing": "linear"
						}
					}
				},
				"left_foot": {
					"rotation": {
						"0.0": {
							"vector": [0, 0, 0]
						},
						"0.25": {
							"vector": [47.5, 0, 0],
							"easing": "linear"
						},
						"0.5": {
							"vector": [0, 0, 0]
						},
						"0.75": {
							"vector": [40, 0, 0],
							"easing": "linear"
						},
						"1.0": {
							"vector": [0, 0, 0],
							"easing": "linear"
						}
					}
				},
				"body": {
					"position": {
						"0.0": {
							"vector": [0, 0, 0]
						},
						"0.25": {
							"vector": [0, -4, 0]
						},
						"0.5": {
							"vector": [0, 0, 0]
						},
						"0.75": {
							"vector": [0, -4, 0]
						},
						"1.0": {
							"vector": [0, 0, 0]
						}
					}
				}
			}
		},
		"attack.slash": {
			"animation_length": 0.5,
			"bones": {
				"body": {
					"position": {
						"0.0": {
							"vector": [0, 0, 0]
						},
						"0.0833": {
							"vector": [0, -3.75, 0],
							"easing": "linear"
						},
						"0.1667": {
							"vector": [0, -7.68, 0]
						},
						"0.5": {
							"vector": [0, 0, 0],
							"easing": "easeInElastic"
						}
					}
				},
				"upper_body": {
					"rotation": {
						"0.0": {
							"vector": [0, 0, 0]
						},
						"0.0833": {
							"vector": [15, 0, 25]
						},
						"0.5": {
							"vector": [0, 0, 0],
							"easing": "easeInElastic"
						}
					}
				},
				"head": {
					"rotation": {
						"0.0": {
							"vector": [0, 0, 0]
						},
						"0.0833": {
							"vector": [-9.47418, -15.19793, -19.77984]
						},
						"0.5": {
							"vector": [0, 0, 0],
							"easing": "easeInElastic"
						}
					}
				},
				"right_arm": {
					"rotation": {
						"0.0": {
							"vector": [0, 0, 0]
						},
						"0.0833": {
							"vector": [-65.8137, -51.14278, 10.56597],
							"easing": "linear"
						},
						"0.1667": {
							"vector": [-67.63908, 78.84286, 7.34304],
							"easing": "linear"
						},
						"0.5": {
							"vector": [0, 0, 0],
							"easing": "easeInElastic"
						}
					}
				},
				"right_forearm": {
					"rotation": {
						"0.0": {
							"vector": [0, 0, 0]
						},
						"0.0833": {
							"vector": [0, 0, -45],
							"easing": "linear"
						},
						"0.1667": {
							"vector": [0, 0, 0],
							"easing": "linear"
						},
						"0.5": {
							"vector": [0, 0, 0],
							"easing": "easeInElastic"
						}
					}
				},
				"left_arm": {
					"rotation": {
						"0.0": {
							"vector": [0, 0, 0]
						},
						"0.0833": {
							"vector": [68.91452, -31.67971, 6.23878],
							"easing": "linear"
						},
						"0.5": {
							"vector": [0, 0, 0],
							"easing": "easeInElastic"
						}
					}
				},
				"left_forearm": {
					"rotation": {
						"0.0": {
							"vector": [0, 0, 0]
						},
						"0.0833": {
							"vector": [-62.5, 0, 0],
							"easing": "linear"
						},
						"0.5": {
							"vector": [0, 0, 0],
							"easing": "easeInElastic"
						}
					}
				},
				"right_leg": {
					"rotation": {
						"0.0": {
							"vector": [0, 0, 0]
						},
						"0.0833": {
							"vector": [50.23421, -15.69986, 16.32495],
							"easing": "linear"
						},
						"0.1667": {
							"vector": [69.41133, -16.10349, 16.74465]
						},
						"0.25": {
							"vector": [71.33325, -13.73469, 14.28153]
						},
						"0.5": {
							"vector": [0, 0, 0],
							"easing": "easeInElastic"
						}
					}
				},
				"right_foot": {
					"rotation": {
						"0.0": {
							"vector": [0, 0, 0]
						},
						"0.0833": {
							"vector": [10, 0, 0],
							"easing": "linear"
						},
						"0.1667": {
							"vector": [4.68, 0, 0]
						},
						"0.5": {
							"vector": [0, 0, 0],
							"easing": "easeInOutBack"
						}
					}
				},
				"left_leg": {
					"rotation": {
						"0.0": {
							"vector": [0, 0, 0]
						},
						"0.0833": {
							"vector": [-34.90802, -36.01729, 7.29199],
							"easing": "linear"
						},
						"0.1667": {
							"vector": [-57.80297, -41.94837, 8.80843]
						},
						"0.5": {
							"vector": [0, 0, 0],
							"easing": "easeInElastic"
						}
					}
				},
				"left_foot": {
					"rotation": {
						"0.0": {
							"vector": [0, 0, 0]
						},
						"0.0833": {
							"vector": [35, 0, 0],
							"easing": "linear"
						},
						"0.1667": {
							"vector": [58.46, 0, 0]
						},
						"0.5": {
							"vector": [0, 0, 0],
							"easing": "easeInElastic"
						}
					}
				}
			}
		},
		"misc.idle": {
			"loop": true,
			"animation_length": 1,
			"bones": {
				"right_arm": {
					"position": {
						"0.0": {
							"vector": [0, 0, 0]
						},
						"0.5": {
							"vector": [0, 1, 0]
						},
						"1.0": {
							"vector": [0, 0, 0]
						}
					}
				},
				"left_arm": {
					"position": {
						"0.0": {
							"vector": [0, 0, 0]
						},
						"0.5": {
							"vector": [0, 1, 0]
						},
						"1.0": {
							"vector": [0, 0, 0]
						}
					}
				},
				"left_forearm": {
					"rotation": {
						"vector": [-5, 0, 0]
					}
				}
			}
		},
		"move.run": {
			"loop": true,
			"animation_length": 0.75,
			"bones": {
				"body": {
					"position": {
						"0.0": {
							"vector": [0, 0, 0]
						},
						"0.0833": {
							"vector": [0, 0, 0]
						},
						"0.1667": {
							"vector": [0, -4, 0]
						},
						"0.2917": {
							"vector": [0, 0, 0]
						},
						"0.4583": {
							"vector": [0, 0, 0]
						},
						"0.5417": {
							"vector": [0, -4, 0]
						},
						"0.75": {
							"vector": [0, 0, 0]
						}
					}
				},
				"spine": {
					"rotation": {
						"0.0": {
							"vector": [0, 0, 0]
						},
						"0.1667": {
							"vector": [0, 0, -2.5]
						},
						"0.5417": {
							"vector": [0, 0, 2.5]
						},
						"0.75": {
							"vector": [0, 0, 0]
						}
					}
				},
				"right_leg": {
					"rotation": {
						"0.0": {
							"vector": [0, 0, 0]
						},
						"0.0833": {
							"vector": [-60, 0, 0]
						},
						"0.1667": {
							"vector": [-40, 0, 0],
							"easing": "linear"
						},
						"0.2917": {
							"vector": [0, 0, 0],
							"easing": "linear"
						},
						"0.4583": {
							"vector": [60, 0, 0]
						},
						"0.5417": {
							"vector": [30, 0, 0],
							"easing": "linear"
						},
						"0.75": {
							"vector": [0, 0, 0],
							"easing": "linear"
						}
					}
				},
				"right_foot": {
					"rotation": {
						"0.0": {
							"vector": [0, 0, 0]
						},
						"0.1667": {
							"vector": [40, 0, 0],
							"easing": "linear"
						},
						"0.2917": {
							"vector": [0, 0, 0],
							"easing": "linear"
						},
						"0.5417": {
							"vector": [60, 0, 0],
							"easing": "linear"
						},
						"0.75": {
							"vector": [0, 0, 0],
							"easing": "linear"
						}
					}
				},
				"left_leg": {
					"rotation": {
						"0.0": {
							"vector": [0, 0, 0]
						},
						"0.0833": {
							"vector": [60, 0, 0]
						},
						"0.2917": {
							"vector": [0, 0, 0],
							"easing": "linear"
						},
						"0.4583": {
							"vector": [-60, 0, 0]
						},
						"0.5417": {
							"vector": [-40, 0, 0],
							"easing": "linear"
						},
						"0.75": {
							"vector": [0, 0, 0]
						}
					}
				},
				"left_foot": {
					"rotation": {
						"0.0": {
							"vector": [0, 0, 0]
						},
						"0.1667": {
							"vector": [60, 0, 0],
							"easing": "linear"
						},
						"0.2917": {
							"vector": [0, 0, 0],
							"easing": "linear"
						},
						"0.375": {
							"vector": [0, 0, 0],
							"easing": "linear"
						},
						"0.5417": {
							"vector": [40, 0, 0],
							"easing": "linear"
						},
						"0.75": {
							"vector": [0, 0, 0],
							"easing": "linear"
						}
					}
				},
				"upper_body": {
					"rotation": {
						"0.0": {
							"vector": [0, 0, 0]
						},
						"0.1667": {
							"vector": [15, 0, 0]
						},
						"0.5417": {
							"vector": [15, 0, 0]
						},
						"0.75": {
							"vector": [0, 0, 0]
						}
					}
				},
				"head": {
					"rotation": {
						"0.0": {
							"vector": [0, 0, 0]
						},
						"0.1667": {
							"vector": [-12.5, 0, 0]
						},
						"0.5417": {
							"vector": [-12.5, 0, 0]
						},
						"0.75": {
							"vector": [0, 0, 0]
						}
					}
				},
				"right_arm": {
					"rotation": {
						"0.0": {
							"vector": [0, 0, 0]
						},
						"0.1667": {
							"vector": [-45, 0, 0],
							"easing": "linear"
						},
						"0.5417": {
							"vector": [45, 0, 0],
							"easing": "linear"
						},
						"0.75": {
							"vector": [0, 0, 0],
							"easing": "linear"
						}
					}
				},
				"right_forearm": {
					"rotation": {
						"0.0": {
							"vector": [0, 0, 0]
						},
						"0.1667": {
							"vector": [-45, 0, 0]
						},
						"0.5417": {
							"vector": [-45, 0, 0]
						},
						"0.75": {
							"vector": [0, 0, 0]
						}
					}
				},
				"left_arm": {
					"rotation": {
						"0.0": {
							"vector": [0, 0, 0]
						},
						"0.1667": {
							"vector": [45, 0, 0],
							"easing": "linear"
						},
						"0.5417": {
							"vector": [-45, 0, 0],
							"easing": "linear"
						},
						"0.75": {
							"vector": [0, 0, 0],
							"easing": "linear"
						}
					}
				},
				"left_forearm": {
					"rotation": {
						"0.0": {
							"vector": [0, 0, 0]
						},
						"0.1667": {
							"vector": [-45, 0, 0]
						},
						"0.5417": {
							"vector": [-45, 0, 0]
						},
						"0.75": {
							"vector": [0, 0, 0]
						}
					}
				}
			}
		}
	},
	"geckolib_format_version": 2
}