{
	"format_version": "1.12.0",
	"minecraft:geometry": [
		{
			"description": {
				"identifier": "geometry.unknown",
				"texture_width": 256,
				"texture_height": 256,
				"visible_bounds_width": 10,
				"visible_bounds_height": 6.5,
				"visible_bounds_offset": [0, 2.75, 0]
			},
			"bones": [
				{
					"name": "hands",
					"pivot": [0, 0, 0]
				},
				{
					"name": "center",
					"parent": "hands",
					"pivot": [-0.5, 27, 16],
					"cubes": [
						{"origin": [-9.5, 12, -9], "size": [18, 25, 11], "uv": [0, 141]}
					]
				},
				{
					"name": "hand",
					"parent": "hands",
					"pivot": [-0.5, 27, 16],
					"rotation": [95, 0, 0],
					"cubes": [
						{"origin": [-10.5, 51.90487, 13.17889], "size": [21, 19, 6], "uv": [108, 94]},
						{"origin": [3.5, 70.90487, 13.17889], "size": [7, 22, 6], "uv": [65, 19]},
						{"origin": [-3.5, 70.90487, 13.17889], "size": [7, 22, 6], "uv": [65, 19]},
						{"origin": [-10.5, 70.90487, 13.17889], "size": [7, 22, 6], "uv": [65, 19]}
					]
				},
				{
					"name": "thumb",
					"parent": "hand",
					"pivot": [-10.5, 27, 16],
					"cubes": [
						{"origin": [-15.5, 52.00487, 12.17889], "size": [6, 20, 6], "uv": [162, 78]}
					]
				},
				{
					"name": "hand4",
					"parent": "hands",
					"pivot": [-0.5, 12, 16],
					"rotation": [-95, 0, 0],
					"cubes": [
						{"origin": [-10.5, -31.90487, 13.17889], "size": [21, 19, 6], "uv": [54, 94]},
						{"origin": [3.5, -53.90487, 13.17889], "size": [7, 22, 6], "uv": [65, 19]},
						{"origin": [-3.5, -53.90487, 13.17889], "size": [7, 22, 6], "uv": [65, 19]},
						{"origin": [-10.5, -53.90487, 13.17889], "size": [7, 22, 6], "uv": [65, 19]}
					]
				},
				{
					"name": "thumb4",
					"parent": "hand4",
					"pivot": [-10.5, 12, 16],
					"cubes": [
						{"origin": [-15.5, -33.00487, 12.17889], "size": [6, 20, 6], "uv": [162, 0]}
					]
				},
				{
					"name": "hand2",
					"parent": "hands",
					"pivot": [6.5, 27, 20],
					"rotation": [37.28135, -4.99523, 92.50954],
					"cubes": [
						{"origin": [-5.67682, 42.08572, -4.81622], "size": [21, 19, 6], "uv": [108, 94]},
						{"origin": [1.32318, 61.08572, -4.81622], "size": [7, 22, 6], "uv": [65, 19]},
						{"origin": [8.32318, 61.08572, -4.81622], "size": [7, 22, 6], "uv": [65, 19]}
					]
				},
				{
					"name": "bone",
					"parent": "hand2",
					"pivot": [4.5, 46, 20],
					"rotation": [0, 0, -15],
					"cubes": [
						{"origin": [-1.69817, 61.13509, -4.81622], "size": [7, 22, 6], "uv": [65, 19]}
					]
				},
				{
					"name": "thumb2",
					"parent": "hand2",
					"pivot": [-3.5, 30, 20],
					"rotation": [0, 0, -22.5],
					"cubes": [
						{"origin": [-4.73806, 42.77042, -5.81622], "size": [6, 20, 6], "uv": [162, 53]}
					]
				},
				{
					"name": "hand3",
					"parent": "hands",
					"pivot": [-10.5, 27, 22],
					"rotation": [37.19223, 5.67633, -113.98446],
					"cubes": [
						{"origin": [-19.02728, 42.03817, -2.81764], "size": [21, 19, 6], "uv": [108, 94]},
						{"origin": [-5.02728, 61.03817, -2.81764], "size": [7, 22, 6], "uv": [65, 19]}
					]
				},
				{
					"name": "bone3",
					"parent": "hand3",
					"pivot": [-10.5, 44, 20],
					"rotation": [2.5, 0, -5],
					"cubes": [
						{"origin": [-10.72603, 61.61582, -2.15472], "size": [7, 22, 6], "uv": [65, 19]}
					]
				},
				{
					"name": "bone2",
					"parent": "hand3",
					"pivot": [-17.5, 44, 20],
					"rotation": [5, 0, -15],
					"cubes": [
						{"origin": [-15.21937, 61.56016, -1.53201], "size": [7, 22, 6], "uv": [65, 19]}
					]
				},
				{
					"name": "thumb3",
					"parent": "hand3",
					"pivot": [-0.5, 30, 22],
					"rotation": [0, 0, 22.5],
					"cubes": [
						{"origin": [-4.97037, 42.83973, -3.81764], "size": [6, 20, 6], "uv": [162, 53]}
					]
				},
				{
					"name": "hands2",
					"pivot": [0, 0, 43]
				},
				{
					"name": "hand5",
					"parent": "hands2",
					"pivot": [7.5, 27, 27],
					"rotation": [-95, 5, 90],
					"cubes": [
						{"origin": [4.65987, 2.62402, 28.13262], "size": [21, 19, 6], "uv": [0, 0]},
						{"origin": [4.67889, 21.5899, 28.1706], "size": [7, 22, 6], "uv": [65, 19]},
						{"origin": [18.67889, 21.5899, 28.1706], "size": [7, 22, 6], "uv": [65, 19]},
						{"origin": [11.67889, 21.5899, 28.1706], "size": [7, 22, 6], "uv": [65, 19]}
					]
				},
				{
					"name": "thumb5",
					"parent": "hand5",
					"pivot": [-2.5, 27, 27],
					"cubes": [
						{"origin": [-0.34013, 2.62402, 29.13262], "size": [6, 20, 6], "uv": [58, 142]}
					]
				},
				{
					"name": "hand6",
					"parent": "hands2",
					"pivot": [-7.5, 27, 27],
					"rotation": [-95, -5, -90],
					"cubes": [
						{"origin": [-25.65987, 2.62402, 28.13262], "size": [21, 19, 6], "uv": [0, 0]},
						{"origin": [-25.67889, 21.5899, 28.1706], "size": [7, 22, 6], "uv": [65, 19]},
						{"origin": [-18.67889, 21.5899, 28.1706], "size": [7, 22, 6], "uv": [65, 19]},
						{"origin": [-11.67889, 21.5899, 28.1706], "size": [7, 22, 6], "uv": [65, 19]}
					]
				},
				{
					"name": "thumb6",
					"parent": "hand6",
					"pivot": [2.5, 27, 27],
					"cubes": [
						{"origin": [-5.65987, 2.62402, 29.13262], "size": [6, 20, 6], "uv": [58, 142]}
					]
				},
				{
					"name": "hand9",
					"parent": "hands2",
					"pivot": [-0.5, 35, 18],
					"rotation": [-15, 0, 0],
					"cubes": [
						{"origin": [-10.5, 28.52952, -7.14815], "size": [21, 19, 6], "uv": [0, 0]}
					]
				},
				{
					"name": "bone9",
					"parent": "hand9",
					"pivot": [-8.5, 54, 20],
					"rotation": [-5, 0, -5],
					"cubes": [
						{"origin": [-11.06394, 45.47402, -6.49446], "size": [7, 22, 6], "uv": [65, 19]}
					]
				},
				{
					"name": "bone8",
					"parent": "hand9",
					"pivot": [1.5, 55, 20],
					"rotation": [-5, 0, 0],
					"cubes": [
						{"origin": [-3.5, 45.4495, -6.49232], "size": [7, 22, 6], "uv": [65, 19]}
					]
				},
				{
					"name": "bone7",
					"parent": "hand9",
					"pivot": [6.5, 55, 20],
					"rotation": [-7.5, 0, 5],
					"cubes": [
						{"origin": [4.06394, 44.45733, -6.1002], "size": [7, 22, 6], "uv": [65, 19]}
					]
				},
				{
					"name": "thumb9",
					"parent": "hand9",
					"pivot": [-10.5, 35, 18],
					"rotation": [0, 0, -15],
					"cubes": [
						{"origin": [-17.17468, 28.75, -6.14815], "size": [6, 20, 6], "uv": [58, 142]}
					]
				},
				{
					"name": "hand10",
					"parent": "hands2",
					"pivot": [-0.5, 14, 21],
					"rotation": [-47.5, 0, 0],
					"cubes": [
						{"origin": [-10.5, -23.43193, 3.11024], "size": [21, 19, 6], "uv": [0, 0]}
					]
				},
				{
					"name": "bone4",
					"parent": "hand10",
					"pivot": [-6.5, -6, 23],
					"rotation": [-34.89121, 3.37562, 3.69066],
					"cubes": [
						{"origin": [-8.32111, -51.6918, 16.74926], "size": [7, 22, 6], "uv": [65, 19]}
					]
				},
				{
					"name": "bone5",
					"parent": "hand10",
					"pivot": [0.5, -5, 24],
					"rotation": [-35, 0, 0],
					"cubes": [
						{"origin": [-3.5, -51.78612, 16.73685], "size": [7, 22, 6], "uv": [65, 19]}
					]
				},
				{
					"name": "bone6",
					"parent": "hand10",
					"pivot": [6.5, -4, 23],
					"rotation": [-37.26905, -4.29357, -6.15518],
					"cubes": [
						{"origin": [0.26476, -51.69302, 17.81186], "size": [7, 22, 6], "uv": [65, 19]}
					]
				},
				{
					"name": "thumb10",
					"parent": "hand10",
					"pivot": [-10.5, 14, 21],
					"rotation": [0, 0, 15],
					"cubes": [
						{"origin": [-10.72946, -23.80388, 4.11024], "size": [6, 20, 6], "uv": [58, 142]}
					]
				},
				{
					"name": "hand7",
					"parent": "hands2",
					"pivot": [9.5, 27, 24],
					"rotation": [-47.28135, 4.99523, 92.50954],
					"cubes": [
						{"origin": [1.67682, 8.70242, 6.10444], "size": [21, 19, 6], "uv": [0, 0]}
					]
				},
				{
					"name": "bone12",
					"parent": "hand7",
					"pivot": [4.5, 41, 20],
					"rotation": [0, 0, -7.5],
					"cubes": [
						{"origin": [-0.73012, 27.57482, 6.10444], "size": [7, 22, 6], "uv": [65, 19]}
					]
				},
				{
					"name": "bone10",
					"parent": "hand7",
					"pivot": [16.5, 45, 28],
					"rotation": [0, 0, 10],
					"cubes": [
						{"origin": [18.82109, 28.3584, 6.10444], "size": [7, 22, 6], "uv": [65, 19]}
					]
				},
				{
					"name": "bone11",
					"parent": "hand7",
					"pivot": [11.5, 41, 20],
					"cubes": [
						{"origin": [8.67682, 27.70242, 6.10444], "size": [7, 22, 6], "uv": [65, 19]}
					]
				},
				{
					"name": "thumb7",
					"parent": "hand7",
					"pivot": [-0.5, 30, 24],
					"rotation": [0, 0, -42.5],
					"cubes": [
						{"origin": [-16.25675, 13.03897, 7.10444], "size": [6, 20, 6], "uv": [58, 142]}
					]
				},
				{
					"name": "hand8",
					"parent": "hands2",
					"pivot": [-12.5, 24, 27],
					"rotation": [-35.73693, 12.42175, -89.91439],
					"cubes": [
						{"origin": [-18.12235, 9.7402, 6.18236], "size": [21, 19, 6], "uv": [0, 0]}
					]
				},
				{
					"name": "bone13",
					"parent": "hand8",
					"pivot": [-8.5, 42, 30],
					"rotation": [0, 0, 5],
					"cubes": [
						{"origin": [-2.89999, 29.26316, 6.18236], "size": [7, 22, 6], "uv": [65, 19]}
					]
				},
				{
					"name": "bone14",
					"parent": "hand8",
					"pivot": [-13.5, 44, 27],
					"cubes": [
						{"origin": [-11.12235, 28.7402, 6.18236], "size": [7, 22, 6], "uv": [65, 19]}
					]
				},
				{
					"name": "bone15",
					"parent": "hand8",
					"pivot": [-20.5, 43, 28],
					"rotation": [0, 0, -7.5],
					"cubes": [
						{"origin": [-20.02963, 28.16027, 6.18236], "size": [7, 22, 6], "uv": [65, 19]}
					]
				},
				{
					"name": "thumb8",
					"parent": "hand8",
					"pivot": [-2.5, 27, 27],
					"rotation": [0, 0, 22.5],
					"cubes": [
						{"origin": [6.92529, 13.8836, 7.18236], "size": [6, 20, 6], "uv": [58, 142]}
					]
				}
			]
		}
	]
}